ado_pr_manager/__init__.py
ado_pr_manager/azdo_client.py
ado_pr_manager/config.py
ado_pr_manager/server.py
ado_pr_manager-0.1.11.dist-info/METADATA
ado_pr_manager-0.1.11.dist-info/WHEEL
ado_pr_manager-0.1.11.dist-info/entry_points.txt
ado_pr_manager-0.1.11.dist-info/RECORD
