Metadata-Version: 2.4
Name: ado-pr-manager
Version: 0.1.11
Summary: MCP server for managing Azure DevOps Pull Requests
Project-URL: Repository, https://github.com/om-surushe/ado-pr-manager
Project-URL: Homepage, https://github.com/om-surushe/ado-pr-manager
Requires-Python: >=3.10
Requires-Dist: black
Requires-Dist: build
Requires-Dist: flake8
Requires-Dist: mcp
Requires-Dist: pre-commit
Requires-Dist: pydantic
Requires-Dist: pytest
Requires-Dist: pytest-mock
Requires-Dist: python-dotenv
Requires-Dist: requests
Requires-Dist: twine
Requires-Dist: typer
